Workbook

Sheet Guide
A1: Rental Tracker: handover guide
A2: Portfolio demo by Rodrigo Matoso. All names, addresses and amounts are fictitious.
A4: What it does
B5: Records every rent payment, flags anything late or partial, applies late fees automatically, calculates each shareholder's return, and prints a one-page report per property.
A6: Daily use (2 minutes)
A7: 1 | B7: Payments tab: add a row per payment received. Type only the blue columns: date, tenancy ID (drop-down), rent period (1st of the month it pays), amounts, method.
A8: 2 | B8: Expenses tab: add any cost paid for a property.
A9: 3 | B9: Dashboard: arrears, collection rate and the next distribution update instantly.
A10: Monthly / quarterly
A11: 4 | B11: Property Report: pick a property in the yellow cell and print or export to PDF.
A12: 5 | B12: When you pay shareholders, record it in Distributions. 'Next distribution' drops to zero for what was paid.
A13: How arrears are calculated
B14: Rent Schedule creates one line per tenancy per month. Balance = rent due + late fee - rent paid - fee paid. A late fee applies when payment arrives after the due date plus the grace days set in Tenancies.
B15: Status colours: green Paid, yellow Paid late, amber Partial / Fee due, red Overdue.
A16: How shareholder returns work
B17: Net income per property = collected - expenses - management fee (Settings). Each shareholder earns their ownership % of each property's net income, so returns vary by property performance.
A18: Adding a new tenancy or month
B19: Add the tenancy in Tenancies, then add its monthly lines in Rent Schedule (copy an existing block and change the Tenancy ID and Period). In the Google Sheets version this is generated automatically with ARRAYFORMULA.
A20: Colour code
B21: Blue text = typed input. Green text = pulled from another tab. Black = formula. Yellow fill = setting you may change.
A22: Optional alerts
B23: The companion Apps Script (rental_tracker_alerts.gs) emails a list of overdue items every morning when the file is used in Google Sheets.

Sheet Dashboard
A1: Rental Portfolio Dashboard
A2: Demo portfolio with fictitious data. Built in Excel / Google Sheets with formulas only.
A3: As of: | B3: =Settings!$B$4 -> 46318
A5: Key figures
A6: Rent due to date | B6: =SUMIFS('Rent Schedule'!$F$5:$F$28,'Rent Schedule'!$E$5:$E$28,"<="&Settings!$B$4) -> 19100
A7: Rent collected | B7: =SUM('Rent Schedule'!$G$5:$G$28) -> 17125
A8: Collection rate | B8: =IF(B6=0,0,MIN(B6,B7)/B6) -> 0.89659686
A9: Total arrears (incl. fees) | B9: =SUM('Rent Schedule'!$L$5:$L$28) -> 2135
A10: Items needing action | B10: =COUNTIF('Rent Schedule'!$M$5:$M$28,"Overdue")+COUNTIF('Rent Schedule'!$M$5:$M$28,"Partial")+COUNTIF('Rent Schedule'!$M$5:$M$28,"Fee due") -> 3
A11: Next distribution (all shareholders) | B11: =Ownership!H18 -> 8556.8
A14: By property
A15: Property ID | B15: Address | C15: Rent due to date (£) | D15: Collected (£) | E15: Arrears (£) | F15: Expenses (£) | G15: Mgmt fee (£) | H15: Net income (£) | I15: Collection rate | J15: Status
A16: =Properties!A5 -> P01 | B16: =Properties!B5 -> 12 Elm Road, Birmingham B15 | C16: =SUMIFS('Rent Schedule'!$F$5:$F$28,'Rent Schedule'!$B$5:$B$28,A16,'Rent Schedule'!$E$5:$E$28,"<="&Settings!$B$4) -> 3800 | D16: =SUMIFS('Rent Schedule'!$G$5:$G$28,'Rent Schedule'!$B$5:$B$28,A16)+SUMIFS('Rent Schedule'!$K$5:$K$28,'Rent Schedule'!$B$5:$B$28,A16) -> 3800 | E16: =SUMIFS('Rent Schedule'!$L$5:$L$28,'Rent Schedule'!$B$5:$B$28,A16) -> 50 | F16: =SUMIFS(Expenses!$D$5:$D$104,Expenses!$B$5:$B$104,A16,Expenses!$A$5:$A$104,"<="&Settings!$B$4) -> 300 | G16: =D16*Settings!$B$5 -> 304 | H16: =D16-F16-G16 -> 3196 | I16: =IF(C16=0,0,MIN(1,SUMIFS('Rent Schedule'!$G$5:$G$28,'Rent Schedule'!$B$5:$B$28,A16)/C16)) -> 1 | J16: =IF(E16>0,"Arrears","OK") -> Arrears
A17: =Properties!A6 -> P02 | B17: =Properties!B6 -> 48 Oak Street, Birmingham B29 | C17: =SUMIFS('Rent Schedule'!$F$5:$F$28,'Rent Schedule'!$B$5:$B$28,A17,'Rent Schedule'!$E$5:$E$28,"<="&Settings!$B$4) -> 5400 | D17: =SUMIFS('Rent Schedule'!$G$5:$G$28,'Rent Schedule'!$B$5:$B$28,A17)+SUMIFS('Rent Schedule'!$K$5:$K$28,'Rent Schedule'!$B$5:$B$28,A17) -> 5440 | E17: =SUMIFS('Rent Schedule'!$L$5:$L$28,'Rent Schedule'!$B$5:$B$28,A17) -> 0 | F17: =SUMIFS(Expenses!$D$5:$D$104,Expenses!$B$5:$B$104,A17,Expenses!$A$5:$A$104,"<="&Settings!$B$4) -> 495 | G17: =D17*Settings!$B$5 -> 435.2 | H17: =D17-F17-G17 -> 4509.8 | I17: =IF(C17=0,0,MIN(1,SUMIFS('Rent Schedule'!$G$5:$G$28,'Rent Schedule'!$B$5:$B$28,A17)/C17)) -> 1 | J17: =IF(E17>0,"Arrears","OK") -> OK
A18: =Properties!A7 -> P03 | B18: =Properties!B7 -> 7 Canal View, Birmingham B1 | C18: =SUMIFS('Rent Schedule'!$F$5:$F$28,'Rent Schedule'!$B$5:$B$28,A18,'Rent Schedule'!$E$5:$E$28,"<="&Settings!$B$4) -> 3500 | D18: =SUMIFS('Rent Schedule'!$G$5:$G$28,'Rent Schedule'!$B$5:$B$28,A18)+SUMIFS('Rent Schedule'!$K$5:$K$28,'Rent Schedule'!$B$5:$B$28,A18) -> 3125 | E18: =SUMIFS('Rent Schedule'!$L$5:$L$28,'Rent Schedule'!$B$5:$B$28,A18) -> 410 | F18: =SUMIFS(Expenses!$D$5:$D$104,Expenses!$B$5:$B$104,A18,Expenses!$A$5:$A$104,"<="&Settings!$B$4) -> 600 | G18: =D18*Settings!$B$5 -> 250 | H18: =D18-F18-G18 -> 2275 | I18: =IF(C18=0,0,MIN(1,SUMIFS('Rent Schedule'!$G$5:$G$28,'Rent Schedule'!$B$5:$B$28,A18)/C18)) -> 0.89285714 | J18: =IF(E18>0,"Arrears","OK") -> Arrears
A19: =Properties!A8 -> P04 | B19: =Properties!B8 -> 221 Bristol Road, Birmingham B5 | C19: =SUMIFS('Rent Schedule'!$F$5:$F$28,'Rent Schedule'!$B$5:$B$28,A19,'Rent Schedule'!$E$5:$E$28,"<="&Settings!$B$4) -> 6400 | D19: =SUMIFS('Rent Schedule'!$G$5:$G$28,'Rent Schedule'!$B$5:$B$28,A19)+SUMIFS('Rent Schedule'!$K$5:$K$28,'Rent Schedule'!$B$5:$B$28,A19) -> 4800 | E19: =SUMIFS('Rent Schedule'!$L$5:$L$28,'Rent Schedule'!$B$5:$B$28,A19) -> 1675 | F19: =SUMIFS(Expenses!$D$5:$D$104,Expenses!$B$5:$B$104,A19,Expenses!$A$5:$A$104,"<="&Settings!$B$4) -> 940 | G19: =D19*Settings!$B$5 -> 384 | H19: =D19-F19-G19 -> 3476 | I19: =IF(C19=0,0,MIN(1,SUMIFS('Rent Schedule'!$G$5:$G$28,'Rent Schedule'!$B$5:$B$28,A19)/C19)) -> 0.75 | J19: =IF(E19>0,"Arrears","OK") -> Arrears
A20: Total | C20: =SUM(C16:C19) -> 19100 | D20: =SUM(D16:D19) -> 17165 | E20: =SUM(E16:E19) -> 2135 | F20: =SUM(F16:F19) -> 2335 | G20: =SUM(G16:G19) -> 1373.2 | H20: =SUM(H16:H19) -> 13456.8 | I20: =IF(C20=0,0,MIN(1,SUM('Rent Schedule'!$G$5:$G$28)/C20)) -> 0.89659686
A22: Shareholders
A23: Shareholder | B23: Earned to date (£) | C23: Distributed (£) | D23: Next distribution (£)
A24: =Ownership!A15 -> R. Hughes | B24: =Ownership!F15 -> 4583.76 | C24: =Ownership!G15 -> 1800 | D24: =Ownership!H15 -> 2783.76
A25: =Ownership!A16 -> L. Bennett | B25: =Ownership!F16 -> 5235.52 | C25: =Ownership!G16 -> 1600 | D25: =Ownership!H16 -> 3635.52
A26: =Ownership!A17 -> K. Shah | B26: =Ownership!F17 -> 3637.52 | C26: =Ownership!G17 -> 1500 | D26: =Ownership!H17 -> 2137.52

Sheet Property Report
A1: Property report
A2: Pick a property in the yellow cell. The page is laid out to print on one A4 sheet.
A4: Property | B4: P04
A5: Address | B5: =IFERROR(INDEX(Properties!$B$5:$B$50,MATCH($B$4,Properties!$A$5:$A$50,0)),"") -> 221 Bristol Road, Birmingham B5
A6: Tenant | B6: =IFERROR(INDEX(Tenancies!$D$5:$D$50,MATCH($B$4,Tenancies!$B$5:$B$50,0)),"Vacant") -> A. Okafor
A7: Monthly rent | B7: =IFERROR(INDEX(Tenancies!$G$5:$G$50,MATCH($B$4,Tenancies!$B$5:$B$50,0)),0) -> 1600
A8: Tenancy ends | B8: =IFERROR(INDEX(Tenancies!$F$5:$F$50,MATCH($B$4,Tenancies!$B$5:$B$50,0)),"") -> 46335
A9: Report date | B9: =Settings!$B$4 -> 46318
A11: Monthly history
A12: Period | B12: Rent due (£) | C12: Paid (£) | D12: Late fee charged (£) | E12: Balance (£) | F12: Status
A13: 46204 | B13: =SUMIFS('Rent Schedule'!$F$5:$F$28,'Rent Schedule'!$B$5:$B$28,$B$4,'Rent Schedule'!$D$5:$D$28,A13) -> 1600 | C13: =SUMIFS('Rent Schedule'!$G$5:$G$28,'Rent Schedule'!$B$5:$B$28,$B$4,'Rent Schedule'!$D$5:$D$28,A13) -> 1600 | D13: =SUMIFS('Rent Schedule'!$J$5:$J$28,'Rent Schedule'!$B$5:$B$28,$B$4,'Rent Schedule'!$D$5:$D$28,A13) -> 0 | E13: =SUMIFS('Rent Schedule'!$L$5:$L$28,'Rent Schedule'!$B$5:$B$28,$B$4,'Rent Schedule'!$D$5:$D$28,A13) -> 0 | F13: =IFERROR(INDEX('Rent Schedule'!$M$5:$M$28,MATCH(1,INDEX(('Rent Schedule'!$B$5:$B$28=$B$4)*('Rent Schedule'!$D$5:$D$28=A13),0),0)),"") -> Paid
A14: 46235 | B14: =SUMIFS('Rent Schedule'!$F$5:$F$28,'Rent Schedule'!$B$5:$B$28,$B$4,'Rent Schedule'!$D$5:$D$28,A14) -> 1600 | C14: =SUMIFS('Rent Schedule'!$G$5:$G$28,'Rent Schedule'!$B$5:$B$28,$B$4,'Rent Schedule'!$D$5:$D$28,A14) -> 1600 | D14: =SUMIFS('Rent Schedule'!$J$5:$J$28,'Rent Schedule'!$B$5:$B$28,$B$4,'Rent Schedule'!$D$5:$D$28,A14) -> 0 | E14: =SUMIFS('Rent Schedule'!$L$5:$L$28,'Rent Schedule'!$B$5:$B$28,$B$4,'Rent Schedule'!$D$5:$D$28,A14) -> 0 | F14: =IFERROR(INDEX('Rent Schedule'!$M$5:$M$28,MATCH(1,INDEX(('Rent Schedule'!$B$5:$B$28=$B$4)*('Rent Schedule'!$D$5:$D$28=A14),0),0)),"") -> Paid
A15: 46266 | B15: =SUMIFS('Rent Schedule'!$F$5:$F$28,'Rent Schedule'!$B$5:$B$28,$B$4,'Rent Schedule'!$D$5:$D$28,A15) -> 1600 | C15: =SUMIFS('Rent Schedule'!$G$5:$G$28,'Rent Schedule'!$B$5:$B$28,$B$4,'Rent Schedule'!$D$5:$D$28,A15) -> 1600 | D15: =SUMIFS('Rent Schedule'!$J$5:$J$28,'Rent Schedule'!$B$5:$B$28,$B$4,'Rent Schedule'!$D$5:$D$28,A15) -> 0 | E15: =SUMIFS('Rent Schedule'!$L$5:$L$28,'Rent Schedule'!$B$5:$B$28,$B$4,'Rent Schedule'!$D$5:$D$28,A15) -> 0 | F15: =IFERROR(INDEX('Rent Schedule'!$M$5:$M$28,MATCH(1,INDEX(('Rent Schedule'!$B$5:$B$28=$B$4)*('Rent Schedule'!$D$5:$D$28=A15),0),0)),"") -> Paid
A16: 46296 | B16: =SUMIFS('Rent Schedule'!$F$5:$F$28,'Rent Schedule'!$B$5:$B$28,$B$4,'Rent Schedule'!$D$5:$D$28,A16) -> 1600 | C16: =SUMIFS('Rent Schedule'!$G$5:$G$28,'Rent Schedule'!$B$5:$B$28,$B$4,'Rent Schedule'!$D$5:$D$28,A16) -> 0 | D16: =SUMIFS('Rent Schedule'!$J$5:$J$28,'Rent Schedule'!$B$5:$B$28,$B$4,'Rent Schedule'!$D$5:$D$28,A16) -> 75 | E16: =SUMIFS('Rent Schedule'!$L$5:$L$28,'Rent Schedule'!$B$5:$B$28,$B$4,'Rent Schedule'!$D$5:$D$28,A16) -> 1675 | F16: =IFERROR(INDEX('Rent Schedule'!$M$5:$M$28,MATCH(1,INDEX(('Rent Schedule'!$B$5:$B$28=$B$4)*('Rent Schedule'!$D$5:$D$28=A16),0),0)),"") -> Overdue
A17: 46327 | B17: =SUMIFS('Rent Schedule'!$F$5:$F$28,'Rent Schedule'!$B$5:$B$28,$B$4,'Rent Schedule'!$D$5:$D$28,A17) -> 1600 | C17: =SUMIFS('Rent Schedule'!$G$5:$G$28,'Rent Schedule'!$B$5:$B$28,$B$4,'Rent Schedule'!$D$5:$D$28,A17) -> 0 | D17: =SUMIFS('Rent Schedule'!$J$5:$J$28,'Rent Schedule'!$B$5:$B$28,$B$4,'Rent Schedule'!$D$5:$D$28,A17) -> 0 | E17: =SUMIFS('Rent Schedule'!$L$5:$L$28,'Rent Schedule'!$B$5:$B$28,$B$4,'Rent Schedule'!$D$5:$D$28,A17) -> 0 | F17: =IFERROR(INDEX('Rent Schedule'!$M$5:$M$28,MATCH(1,INDEX(('Rent Schedule'!$B$5:$B$28=$B$4)*('Rent Schedule'!$D$5:$D$28=A17),0),0)),"") -> Not due
A18: 46357 | B18: =SUMIFS('Rent Schedule'!$F$5:$F$28,'Rent Schedule'!$B$5:$B$28,$B$4,'Rent Schedule'!$D$5:$D$28,A18) -> 1600 | C18: =SUMIFS('Rent Schedule'!$G$5:$G$28,'Rent Schedule'!$B$5:$B$28,$B$4,'Rent Schedule'!$D$5:$D$28,A18) -> 0 | D18: =SUMIFS('Rent Schedule'!$J$5:$J$28,'Rent Schedule'!$B$5:$B$28,$B$4,'Rent Schedule'!$D$5:$D$28,A18) -> 0 | E18: =SUMIFS('Rent Schedule'!$L$5:$L$28,'Rent Schedule'!$B$5:$B$28,$B$4,'Rent Schedule'!$D$5:$D$28,A18) -> 0 | F18: =IFERROR(INDEX('Rent Schedule'!$M$5:$M$28,MATCH(1,INDEX(('Rent Schedule'!$B$5:$B$28=$B$4)*('Rent Schedule'!$D$5:$D$28=A18),0),0)),"") -> Not due
A19: Total | B19: =SUM(B13:B18) -> 9600 | C19: =SUM(C13:C18) -> 4800 | D19: =SUM(D13:D18) -> 75 | E19: =SUM(E13:E18) -> 1675
A21: Income & expenses to date
A22: Rent and fees collected | B22: =INDEX(Dashboard!$D$16:$D$19,MATCH($B$4,Dashboard!$A$16:$A$19,0)) -> 4800
A23: Less: Repairs & maintenance | B23: =-SUMIFS(Expenses!$D$5:$D$104,Expenses!$B$5:$B$104,$B$4,Expenses!$C$5:$C$104,"Repairs & maintenance",Expenses!$A$5:$A$104,"<="&Settings!$B$4) -> -850
A24: Less: Insurance | B24: =-SUMIFS(Expenses!$D$5:$D$104,Expenses!$B$5:$B$104,$B$4,Expenses!$C$5:$C$104,"Insurance",Expenses!$A$5:$A$104,"<="&Settings!$B$4) -> 0
A25: Less: Service charge | B25: =-SUMIFS(Expenses!$D$5:$D$104,Expenses!$B$5:$B$104,$B$4,Expenses!$C$5:$C$104,"Service charge",Expenses!$A$5:$A$104,"<="&Settings!$B$4) -> 0
A26: Less: Compliance & safety | B26: =-SUMIFS(Expenses!$D$5:$D$104,Expenses!$B$5:$B$104,$B$4,Expenses!$C$5:$C$104,"Compliance & safety",Expenses!$A$5:$A$104,"<="&Settings!$B$4) -> -90
A27: Less: Letting fees | B27: =-SUMIFS(Expenses!$D$5:$D$104,Expenses!$B$5:$B$104,$B$4,Expenses!$C$5:$C$104,"Letting fees",Expenses!$A$5:$A$104,"<="&Settings!$B$4) -> 0
A28: Less: Other | B28: =-SUMIFS(Expenses!$D$5:$D$104,Expenses!$B$5:$B$104,$B$4,Expenses!$C$5:$C$104,"Other",Expenses!$A$5:$A$104,"<="&Settings!$B$4) -> 0
A29: Less: management fee | B29: =-INDEX(Dashboard!$G$16:$G$19,MATCH($B$4,Dashboard!$A$16:$A$19,0)) -> -384
A30: Net income | B30: =SUM(B22:B29) -> 3476
A32: Shareholder split for this property
A33: Shareholder | B33: Ownership % | C33: Share of net income (£)
A34: =Ownership!A15 -> R. Hughes | B34: =INDEX(Ownership!C$5:C$8,MATCH($B$4,Ownership!$A$5:$A$8,0)) -> 0.34 | C34: =B34*$B$30 -> 1181.84
A35: =Ownership!A16 -> L. Bennett | B35: =INDEX(Ownership!D$5:D$8,MATCH($B$4,Ownership!$A$5:$A$8,0)) -> 0.33 | C35: =B35*$B$30 -> 1147.08
A36: =Ownership!A17 -> K. Shah | B36: =INDEX(Ownership!E$5:E$8,MATCH($B$4,Ownership!$A$5:$A$8,0)) -> 0.33 | C36: =B36*$B$30 -> 1147.08

Sheet Payments
A1: Payments ledger
A2: Add one row per payment received. Only the blue columns are typed; grey columns fill in automatically.
A4: Date received | B4: Tenancy ID | C4: Property ID | D4: Tenant | E4: Rent period (1st of month) | F4: Rent amount (£) | G4: Late fee paid (£) | H4: Method | I4: Period status | J4: Notes
A5: 46204 | B5: T01 | C5: =IF(B5="","",IFERROR(INDEX(Tenancies!$B$5:$B$50,MATCH(B5,Tenancies!$A$5:$A$50,0)),"Check ID")) -> P01 | D5: =IF(B5="","",IFERROR(INDEX(Tenancies!$D$5:$D$50,MATCH(B5,Tenancies!$A$5:$A$50,0)),"Check ID")) -> J. Carter | E5: 46204 | F5: 950 | G5: 0 | H5: Standing order | I5: =IF(OR(B5="",E5=""),"",IF(SUMIFS($F$5:$F$304,$B$5:$B$304,B5,$E$5:$E$304,E5)>=IFERROR(INDEX(Tenancies!$G$5:$G$50,MATCH(B5,Tenancies!$A$5:$A$50,0)),0),"Rent complete","Partial")) -> Rent complete
A6: 46204 | B6: T03 | C6: =IF(B6="","",IFERROR(INDEX(Tenancies!$B$5:$B$50,MATCH(B6,Tenancies!$A$5:$A$50,0)),"Check ID")) -> P03 | D6: =IF(B6="","",IFERROR(INDEX(Tenancies!$D$5:$D$50,MATCH(B6,Tenancies!$A$5:$A$50,0)),"Check ID")) -> S. Nowak | E6: 46204 | F6: 875 | G6: 0 | H6: Bank transfer | I6: =IF(OR(B6="",E6=""),"",IF(SUMIFS($F$5:$F$304,$B$5:$B$304,B6,$E$5:$E$304,E6)>=IFERROR(INDEX(Tenancies!$G$5:$G$50,MATCH(B6,Tenancies!$A$5:$A$50,0)),0),"Rent complete","Partial")) -> Rent complete
A7: 46207 | B7: T02 | C7: =IF(B7="","",IFERROR(INDEX(Tenancies!$B$5:$B$50,MATCH(B7,Tenancies!$A$5:$A$50,0)),"Check ID")) -> P02 | D7: =IF(B7="","",IFERROR(INDEX(Tenancies!$D$5:$D$50,MATCH(B7,Tenancies!$A$5:$A$50,0)),"Check ID")) -> M. Patel | E7: 46204 | F7: 1350 | G7: 0 | H7: Bank transfer | I7: =IF(OR(B7="",E7=""),"",IF(SUMIFS($F$5:$F$304,$B$5:$B$304,B7,$E$5:$E$304,E7)>=IFERROR(INDEX(Tenancies!$G$5:$G$50,MATCH(B7,Tenancies!$A$5:$A$50,0)),0),"Rent complete","Partial")) -> Rent complete
A8: 46212 | B8: T04 | C8: =IF(B8="","",IFERROR(INDEX(Tenancies!$B$5:$B$50,MATCH(B8,Tenancies!$A$5:$A$50,0)),"Check ID")) -> P04 | D8: =IF(B8="","",IFERROR(INDEX(Tenancies!$D$5:$D$50,MATCH(B8,Tenancies!$A$5:$A$50,0)),"Check ID")) -> A. Okafor | E8: 46204 | F8: 1600 | G8: 0 | H8: Standing order | I8: =IF(OR(B8="",E8=""),"",IF(SUMIFS($F$5:$F$304,$B$5:$B$304,B8,$E$5:$E$304,E8)>=IFERROR(INDEX(Tenancies!$G$5:$G$50,MATCH(B8,Tenancies!$A$5:$A$50,0)),0),"Rent complete","Partial")) -> Rent complete
A9: 46235 | B9: T01 | C9: =IF(B9="","",IFERROR(INDEX(Tenancies!$B$5:$B$50,MATCH(B9,Tenancies!$A$5:$A$50,0)),"Check ID")) -> P01 | D9: =IF(B9="","",IFERROR(INDEX(Tenancies!$D$5:$D$50,MATCH(B9,Tenancies!$A$5:$A$50,0)),"Check ID")) -> J. Carter | E9: 46235 | F9: 500 | G9: 0 | H9: Standing order | I9: =IF(OR(B9="",E9=""),"",IF(SUMIFS($F$5:$F$304,$B$5:$B$304,B9,$E$5:$E$304,E9)>=IFERROR(INDEX(Tenancies!$G$5:$G$50,MATCH(B9,Tenancies!$A$5:$A$50,0)),0),"Rent complete","Partial")) -> Rent complete | J9: Tenant paid in two parts
A10: 46235 | B10: T03 | C10: =IF(B10="","",IFERROR(INDEX(Tenancies!$B$5:$B$50,MATCH(B10,Tenancies!$A$5:$A$50,0)),"Check ID")) -> P03 | D10: =IF(B10="","",IFERROR(INDEX(Tenancies!$D$5:$D$50,MATCH(B10,Tenancies!$A$5:$A$50,0)),"Check ID")) -> S. Nowak | E10: 46235 | F10: 875 | G10: 0 | H10: Bank transfer | I10: =IF(OR(B10="",E10=""),"",IF(SUMIFS($F$5:$F$304,$B$5:$B$304,B10,$E$5:$E$304,E10)>=IFERROR(INDEX(Tenancies!$G$5:$G$50,MATCH(B10,Tenancies!$A$5:$A$50,0)),0),"Rent complete","Partial")) -> Rent complete
A11: 46238 | B11: T02 | C11: =IF(B11="","",IFERROR(INDEX(Tenancies!$B$5:$B$50,MATCH(B11,Tenancies!$A$5:$A$50,0)),"Check ID")) -> P02 | D11: =IF(B11="","",IFERROR(INDEX(Tenancies!$D$5:$D$50,MATCH(B11,Tenancies!$A$5:$A$50,0)),"Check ID")) -> M. Patel | E11: 46235 | F11: 1350 | G11: 0 | H11: Bank transfer | I11: =IF(OR(B11="",E11=""),"",IF(SUMIFS($F$5:$F$304,$B$5:$B$304,B11,$E$5:$E$304,E11)>=IFERROR(INDEX(Tenancies!$G$5:$G$50,MATCH(B11,Tenancies!$A$5:$A$50,0)),0),"Rent complete","Partial")) -> Rent complete
A12: 46243 | B12: T04 | C12: =IF(B12="","",IFERROR(INDEX(Tenancies!$B$5:$B$50,MATCH(B12,Tenancies!$A$5:$A$50,0)),"Check ID")) -> P04 | D12: =IF(B12="","",IFERROR(INDEX(Tenancies!$D$5:$D$50,MATCH(B12,Tenancies!$A$5:$A$50,0)),"Check ID")) -> A. Okafor | E12: 46235 | F12: 1600 | G12: 0 | H12: Standing order | I12: =IF(OR(B12="",E12=""),"",IF(SUMIFS($F$5:$F$304,$B$5:$B$304,B12,$E$5:$E$304,E12)>=IFERROR(INDEX(Tenancies!$G$5:$G$50,MATCH(B12,Tenancies!$A$5:$A$50,0)),0),"Rent complete","Partial")) -> Rent complete
A13: 46254 | B13: T01 | C13: =IF(B13="","",IFERROR(INDEX(Tenancies!$B$5:$B$50,MATCH(B13,Tenancies!$A$5:$A$50,0)),"Check ID")) -> P01 | D13: =IF(B13="","",IFERROR(INDEX(Tenancies!$D$5:$D$50,MATCH(B13,Tenancies!$A$5:$A$50,0)),"Check ID")) -> J. Carter | E13: 46235 | F13: 450 | G13: 0 | H13: Bank transfer | I13: =IF(OR(B13="",E13=""),"",IF(SUMIFS($F$5:$F$304,$B$5:$B$304,B13,$E$5:$E$304,E13)>=IFERROR(INDEX(Tenancies!$G$5:$G$50,MATCH(B13,Tenancies!$A$5:$A$50,0)),0),"Rent complete","Partial")) -> Rent complete | J13: Balance; late fee still owed
A14: 46266 | B14: T01 | C14: =IF(B14="","",IFERROR(INDEX(Tenancies!$B$5:$B$50,MATCH(B14,Tenancies!$A$5:$A$50,0)),"Check ID")) -> P01 | D14: =IF(B14="","",IFERROR(INDEX(Tenancies!$D$5:$D$50,MATCH(B14,Tenancies!$A$5:$A$50,0)),"Check ID")) -> J. Carter | E14: 46266 | F14: 950 | G14: 0 | H14: Standing order | I14: =IF(OR(B14="",E14=""),"",IF(SUMIFS($F$5:$F$304,$B$5:$B$304,B14,$E$5:$E$304,E14)>=IFERROR(INDEX(Tenancies!$G$5:$G$50,MATCH(B14,Tenancies!$A$5:$A$50,0)),0),"Rent complete","Partial")) -> Rent complete
A15: 46266 | B15: T03 | C15: =IF(B15="","",IFERROR(INDEX(Tenancies!$B$5:$B$50,MATCH(B15,Tenancies!$A$5:$A$50,0)),"Check ID")) -> P03 | D15: =IF(B15="","",IFERROR(INDEX(Tenancies!$D$5:$D$50,MATCH(B15,Tenancies!$A$5:$A$50,0)),"Check ID")) -> S. Nowak | E15: 46266 | F15: 875 | G15: 0 | H15: Bank transfer | I15: =IF(OR(B15="",E15=""),"",IF(SUMIFS($F$5:$F$304,$B$5:$B$304,B15,$E$5:$E$304,E15)>=IFERROR(INDEX(Tenancies!$G$5:$G$50,MATCH(B15,Tenancies!$A$5:$A$50,0)),0),"Rent complete","Partial")) -> Rent complete
A16: 46274 | B16: T04 | C16: =IF(B16="","",IFERROR(INDEX(Tenancies!$B$5:$B$50,MATCH(B16,Tenancies!$A$5:$A$50,0)),"Check ID")) -> P04 | D16: =IF(B16="","",IFERROR(INDEX(Tenancies!$D$5:$D$50,MATCH(B16,Tenancies!$A$5:$A$50,0)),"Check ID")) -> A. Okafor | E16: 46266 | F16: 1600 | G16: 0 | H16: Standing order | I16: =IF(OR(B16="",E16=""),"",IF(SUMIFS($F$5:$F$304,$B$5:$B$304,B16,$E$5:$E$304,E16)>=IFERROR(INDEX(Tenancies!$G$5:$G$50,MATCH(B16,Tenancies!$A$5:$A$50,0)),0),"Rent complete","Partial")) -> Rent complete
A17: 46280 | B17: T02 | C17: =IF(B17="","",IFERROR(INDEX(Tenancies!$B$5:$B$50,MATCH(B17,Tenancies!$A$5:$A$50,0)),"Check ID")) -> P02 | D17: =IF(B17="","",IFERROR(INDEX(Tenancies!$D$5:$D$50,MATCH(B17,Tenancies!$A$5:$A$50,0)),"Check ID")) -> M. Patel | E17: 46266 | F17: 1350 | G17: 40 | H17: Bank transfer | I17: =IF(OR(B17="",E17=""),"",IF(SUMIFS($F$5:$F$304,$B$5:$B$304,B17,$E$5:$E$304,E17)>=IFERROR(INDEX(Tenancies!$G$5:$G$50,MATCH(B17,Tenancies!$A$5:$A$50,0)),0),"Rent complete","Partial")) -> Rent complete | J17: Paid 10 days late incl. late fee
A18: 46296 | B18: T01 | C18: =IF(B18="","",IFERROR(INDEX(Tenancies!$B$5:$B$50,MATCH(B18,Tenancies!$A$5:$A$50,0)),"Check ID")) -> P01 | D18: =IF(B18="","",IFERROR(INDEX(Tenancies!$D$5:$D$50,MATCH(B18,Tenancies!$A$5:$A$50,0)),"Check ID")) -> J. Carter | E18: 46296 | F18: 950 | G18: 0 | H18: Standing order | I18: =IF(OR(B18="",E18=""),"",IF(SUMIFS($F$5:$F$304,$B$5:$B$304,B18,$E$5:$E$304,E18)>=IFERROR(INDEX(Tenancies!$G$5:$G$50,MATCH(B18,Tenancies!$A$5:$A$50,0)),0),"Rent complete","Partial")) -> Rent complete
A19: 46296 | B19: T03 | C19: =IF(B19="","",IFERROR(INDEX(Tenancies!$B$5:$B$50,MATCH(B19,Tenancies!$A$5:$A$50,0)),"Check ID")) -> P03 | D19: =IF(B19="","",IFERROR(INDEX(Tenancies!$D$5:$D$50,MATCH(B19,Tenancies!$A$5:$A$50,0)),"Check ID")) -> S. Nowak | E19: 46296 | F19: 500 | G19: 0 | H19: Bank transfer | I19: =IF(OR(B19="",E19=""),"",IF(SUMIFS($F$5:$F$304,$B$5:$B$304,B19,$E$5:$E$304,E19)>=IFERROR(INDEX(Tenancies!$G$5:$G$50,MATCH(B19,Tenancies!$A$5:$A$50,0)),0),"Rent complete","Partial")) -> Partial | J19: Partial: tenant promised balance
A20: 46299 | B20: T02 | C20: =IF(B20="","",IFERROR(INDEX(Tenancies!$B$5:$B$50,MATCH(B20,Tenancies!$A$5:$A$50,0)),"Check ID")) -> P02 | D20: =IF(B20="","",IFERROR(INDEX(Tenancies!$D$5:$D$50,MATCH(B20,Tenancies!$A$5:$A$50,0)),"Check ID")) -> M. Patel | E20: 46296 | F20: 1350 | G20: 0 | H20: Bank transfer | I20: =IF(OR(B20="",E20=""),"",IF(SUMIFS($F$5:$F$304,$B$5:$B$304,B20,$E$5:$E$304,E20)>=IFERROR(INDEX(Tenancies!$G$5:$G$50,MATCH(B20,Tenancies!$A$5:$A$50,0)),0),"Rent complete","Partial")) -> Rent complete
C21: =IF(B21="","",IFERROR(INDEX(Tenancies!$B$5:$B$50,MATCH(B21,Tenancies!$A$5:$A$50,0)),"Check ID")) | D21: =IF(B21="","",IFERROR(INDEX(Tenancies!$D$5:$D$50,MATCH(B21,Tenancies!$A$5:$A$50,0)),"Check ID")) | I21: =IF(OR(B21="",E21=""),"",IF(SUMIFS($F$5:$F$304,$B$5:$B$304,B21,$E$5:$E$304,E21)>=IFERROR(INDEX(Tenancies!$G$5:$G$50,MATCH(B21,Tenancies!$A$5:$A$50,0)),0),"Rent complete","Partial"))
C22: =IF(B22="","",IFERROR(INDEX(Tenancies!$B$5:$B$50,MATCH(B22,Tenancies!$A$5:$A$50,0)),"Check ID")) | D22: =IF(B22="","",IFERROR(INDEX(Tenancies!$D$5:$D$50,MATCH(B22,Tenancies!$A$5:$A$50,0)),"Check ID")) | I22: =IF(OR(B22="",E22=""),"",IF(SUMIFS($F$5:$F$304,$B$5:$B$304,B22,$E$5:$E$304,E22)>=IFERROR(INDEX(Tenancies!$G$5:$G$50,MATCH(B22,Tenancies!$A$5:$A$50,0)),0),"Rent complete","Partial"))
C23: =IF(B23="","",IFERROR(INDEX(Tenancies!$B$5:$B$50,MATCH(B23,Tenancies!$A$5:$A$50,0)),"Check ID")) | D23: =IF(B23="","",IFERROR(INDEX(Tenancies!$D$5:$D$50,MATCH(B23,Tenancies!$A$5:$A$50,0)),"Check ID")) | I23: =IF(OR(B23="",E23=""),"",IF(SUMIFS($F$5:$F$304,$B$5:$B$304,B23,$E$5:$E$304,E23)>=IFERROR(INDEX(Tenancies!$G$5:$G$50,MATCH(B23,Tenancies!$A$5:$A$50,0)),0),"Rent complete","Partial"))
C24: =IF(B24="","",IFERROR(INDEX(Tenancies!$B$5:$B$50,MATCH(B24,Tenancies!$A$5:$A$50,0)),"Check ID")) | D24: =IF(B24="","",IFERROR(INDEX(Tenancies!$D$5:$D$50,MATCH(B24,Tenancies!$A$5:$A$50,0)),"Check ID")) | I24: =IF(OR(B24="",E24=""),"",IF(SUMIFS($F$5:$F$304,$B$5:$B$304,B24,$E$5:$E$304,E24)>=IFERROR(INDEX(Tenancies!$G$5:$G$50,MATCH(B24,Tenancies!$A$5:$A$50,0)),0),"Rent complete","Partial"))
C25: =IF(B25="","",IFERROR(INDEX(Tenancies!$B$5:$B$50,MATCH(B25,Tenancies!$A$5:$A$50,0)),"Check ID")) | D25: =IF(B25="","",IFERROR(INDEX(Tenancies!$D$5:$D$50,MATCH(B25,Tenancies!$A$5:$A$50,0)),"Check ID")) | I25: =IF(OR(B25="",E25=""),"",IF(SUMIFS($F$5:$F$304,$B$5:$B$304,B25,$E$5:$E$304,E25)>=IFERROR(INDEX(Tenancies!$G$5:$G$50,MATCH(B25,Tenancies!$A$5:$A$50,0)),0),"Rent complete","Partial"))
C26: =IF(B26="","",IFERROR(INDEX(Tenancies!$B$5:$B$50,MATCH(B26,Tenancies!$A$5:$A$50,0)),"Check ID")) | D26: =IF(B26="","",IFERROR(INDEX(Tenancies!$D$5:$D$50,MATCH(B26,Tenancies!$A$5:$A$50,0)),"Check ID")) | I26: =IF(OR(B26="",E26=""),"",IF(SUMIFS($F$5:$F$304,$B$5:$B$304,B26,$E$5:$E$304,E26)>=IFERROR(INDEX(Tenancies!$G$5:$G$50,MATCH(B26,Tenancies!$A$5:$A$50,0)),0),"Rent complete","Partial"))
C27: =IF(B27="","",IFERROR(INDEX(Tenancies!$B$5:$B$50,MATCH(B27,Tenancies!$A$5:$A$50,0)),"Check ID")) | D27: =IF(B27="","",IFERROR(INDEX(Tenancies!$D$5:$D$50,MATCH(B27,Tenancies!$A$5:$A$50,0)),"Check ID")) | I27: =IF(OR(B27="",E27=""),"",IF(SUMIFS($F$5:$F$304,$B$5:$B$304,B27,$E$5:$E$304,E27)>=IFERROR(INDEX(Tenancies!$G$5:$G$50,MATCH(B27,Tenancies!$A$5:$A$50,0)),0),"Rent complete","Partial"))
C28: =IF(B28="","",IFERROR(INDEX(Tenancies!$B$5:$B$50,MATCH(B28,Tenancies!$A$5:$A$50,0)),"Check ID")) | D28: =IF(B28="","",IFERROR(INDEX(Tenancies!$D$5:$D$50,MATCH(B28,Tenancies!$A$5:$A$50,0)),"Check ID")) | I28: =IF(OR(B28="",E28=""),"",IF(SUMIFS($F$5:$F$304,$B$5:$B$304,B28,$E$5:$E$304,E28)>=IFERROR(INDEX(Tenancies!$G$5:$G$50,MATCH(B28,Tenancies!$A$5:$A$50,0)),0),"Rent complete","Partial"))
C29: =IF(B29="","",IFERROR(INDEX(Tenancies!$B$5:$B$50,MATCH(B29,Tenancies!$A$5:$A$50,0)),"Check ID")) | D29: =IF(B29="","",IFERROR(INDEX(Tenancies!$D$5:$D$50,MATCH(B29,Tenancies!$A$5:$A$50,0)),"Check ID")) | I29: =IF(OR(B29="",E29=""),"",IF(SUMIFS($F$5:$F$304,$B$5:$B$304,B29,$E$5:$E$304,E29)>=IFERROR(INDEX(Tenancies!$G$5:$G$50,MATCH(B29,Tenancies!$A$5:$A$50,0)),0),"Rent complete","Partial"))
C30: =IF(B30="","",IFERROR(INDEX(Tenancies!$B$5:$B$50,MATCH(B30,Tenancies!$A$5:$A$50,0)),"Check ID")) | D30: =IF(B30="","",IFERROR(INDEX(Tenancies!$D$5:$D$50,MATCH(B30,Tenancies!$A$5:$A$50,0)),"Check ID")) | I30: =IF(OR(B30="",E30=""),"",IF(SUMIFS($F$5:$F$304,$B$5:$B$304,B30,$E$5:$E$304,E30)>=IFERROR(INDEX(Tenancies!$G$5:$G$50,MATCH(B30,Tenancies!$A$5:$A$50,0)),0),"Rent complete","Partial"))
C31: =IF(B31="","",IFERROR(INDEX(Tenancies!$B$5:$B$50,MATCH(B31,Tenancies!$A$5:$A$50,0)),"Check ID")) | D31: =IF(B31="","",IFERROR(INDEX(Tenancies!$D$5:$D$50,MATCH(B31,Tenancies!$A$5:$A$50,0)),"Check ID")) | I31: =IF(OR(B31="",E31=""),"",IF(SUMIFS($F$5:$F$304,$B$5:$B$304,B31,$E$5:$E$304,E31)>=IFERROR(INDEX(Tenancies!$G$5:$G$50,MATCH(B31,Tenancies!$A$5:$A$50,0)),0),"Rent complete","Partial"))
C32: =IF(B32="","",IFERROR(INDEX(Tenancies!$B$5:$B$50,MATCH(B32,Tenancies!$A$5:$A$50,0)),"Check ID")) | D32: =IF(B32="","",IFERROR(INDEX(Tenancies!$D$5:$D$50,MATCH(B32,Tenancies!$A$5:$A$50,0)),"Check ID")) | I32: =IF(OR(B32="",E32=""),"",IF(SUMIFS($F$5:$F$304,$B$5:$B$304,B32,$E$5:$E$304,E32)>=IFERROR(INDEX(Tenancies!$G$5:$G$50,MATCH(B32,Tenancies!$A$5:$A$50,0)),0),"Rent complete","Partial"))
... C304: =IF(B304="","",IFERROR(INDEX(Tenancies!$B$5:$B$50,MATCH(B304,Tenancies!$A$5:$A$50,0)),"Check ID")) | D304: =IF(B304="","",IFERROR(INDEX(Tenancies!$D$5:$D$50,MATCH(B304,Tenancies!$A$5:$A$50,0)),"Check ID")) | I304: =IF(OR(B304="",E304=""),"",IF(SUMIFS($F$5:$F$304,$B$5:$B$304,B304,$E$5:$E$304,E304)>=IFERROR(INDEX(Tenancies!$G$5:$G$50,MATCH(B304,Tenancies!$A$5:$A$50,0)),0),"Rent complete","Partial"))

Sheet Rent Schedule
A1: Rent schedule & arrears
A2: One row per tenancy per month. Everything here is calculated: do not type in this tab.
A4: Tenancy ID | B4: Property ID | C4: Tenant | D4: Period | E4: Due date | F4: Rent due (£) | G4: Rent paid (£) | H4: Last payment | I4: Days late | J4: Late fee due (£) | K4: Late fee paid (£) | L4: Balance (£) | M4: Status
A5: T01 | B5: =IFERROR(INDEX(Tenancies!$B$5:$B$50,MATCH(A5,Tenancies!$A$5:$A$50,0)),"") -> P01 | C5: =IFERROR(INDEX(Tenancies!$D$5:$D$50,MATCH(A5,Tenancies!$A$5:$A$50,0)),"") -> J. Carter | D5: 46204 | E5: =DATE(YEAR(D5),MONTH(D5),INDEX(Tenancies!$H$5:$H$50,MATCH(A5,Tenancies!$A$5:$A$50,0))) -> 46204 | F5: =INDEX(Tenancies!$G$5:$G$50,MATCH(A5,Tenancies!$A$5:$A$50,0)) -> 950 | G5: =SUMIFS(Payments!$F$5:$F$304,Payments!$B$5:$B$304,A5,Payments!$E$5:$E$304,D5) -> 950 | H5: =IF(G5=0,"",_xlfn.MAXIFS(Payments!$A$5:$A$304,Payments!$B$5:$B$304,A5,Payments!$E$5:$E$304,D5)) -> 46204 | I5: =IF(E5>Settings!$B$4,0,IF(G5>=F5,MAX(0,H5-E5),Settings!$B$4-E5)) -> 0 | J5: =IF(I5>INDEX(Tenancies!$I$5:$I$50,MATCH(A5,Tenancies!$A$5:$A$50,0)),INDEX(Tenancies!$J$5:$J$50,MATCH(A5,Tenancies!$A$5:$A$50,0)),0) -> 0 | K5: =SUMIFS(Payments!$G$5:$G$304,Payments!$B$5:$B$304,A5,Payments!$E$5:$E$304,D5) -> 0 | L5: =IF(E5>Settings!$B$4,0,MAX(0,F5+J5-G5-K5)) -> 0 | M5: =IF(E5>Settings!$B$4,"Not due",IF(L5<=0,IF(I5>INDEX(Tenancies!$I$5:$I$50,MATCH(A5,Tenancies!$A$5:$A$50,0)),"Paid late","Paid"),IF(G5>=F5,"Fee due",IF(G5>0,"Partial","Overdue")))) -> Paid
A6: T01 | B6: =IFERROR(INDEX(Tenancies!$B$5:$B$50,MATCH(A6,Tenancies!$A$5:$A$50,0)),"") -> P01 | C6: =IFERROR(INDEX(Tenancies!$D$5:$D$50,MATCH(A6,Tenancies!$A$5:$A$50,0)),"") -> J. Carter | D6: 46235 | E6: =DATE(YEAR(D6),MONTH(D6),INDEX(Tenancies!$H$5:$H$50,MATCH(A6,Tenancies!$A$5:$A$50,0))) -> 46235 | F6: =INDEX(Tenancies!$G$5:$G$50,MATCH(A6,Tenancies!$A$5:$A$50,0)) -> 950 | G6: =SUMIFS(Payments!$F$5:$F$304,Payments!$B$5:$B$304,A6,Payments!$E$5:$E$304,D6) -> 950 | H6: =IF(G6=0,"",_xlfn.MAXIFS(Payments!$A$5:$A$304,Payments!$B$5:$B$304,A6,Payments!$E$5:$E$304,D6)) -> 46254 | I6: =IF(E6>Settings!$B$4,0,IF(G6>=F6,MAX(0,H6-E6),Settings!$B$4-E6)) -> 19 | J6: =IF(I6>INDEX(Tenancies!$I$5:$I$50,MATCH(A6,Tenancies!$A$5:$A$50,0)),INDEX(Tenancies!$J$5:$J$50,MATCH(A6,Tenancies!$A$5:$A$50,0)),0) -> 50 | K6: =SUMIFS(Payments!$G$5:$G$304,Payments!$B$5:$B$304,A6,Payments!$E$5:$E$304,D6) -> 0 | L6: =IF(E6>Settings!$B$4,0,MAX(0,F6+J6-G6-K6)) -> 50 | M6: =IF(E6>Settings!$B$4,"Not due",IF(L6<=0,IF(I6>INDEX(Tenancies!$I$5:$I$50,MATCH(A6,Tenancies!$A$5:$A$50,0)),"Paid late","Paid"),IF(G6>=F6,"Fee due",IF(G6>0,"Partial","Overdue")))) -> Fee due
A7: T01 | B7: =IFERROR(INDEX(Tenancies!$B$5:$B$50,MATCH(A7,Tenancies!$A$5:$A$50,0)),"") -> P01 | C7: =IFERROR(INDEX(Tenancies!$D$5:$D$50,MATCH(A7,Tenancies!$A$5:$A$50,0)),"") -> J. Carter | D7: 46266 | E7: =DATE(YEAR(D7),MONTH(D7),INDEX(Tenancies!$H$5:$H$50,MATCH(A7,Tenancies!$A$5:$A$50,0))) -> 46266 | F7: =INDEX(Tenancies!$G$5:$G$50,MATCH(A7,Tenancies!$A$5:$A$50,0)) -> 950 | G7: =SUMIFS(Payments!$F$5:$F$304,Payments!$B$5:$B$304,A7,Payments!$E$5:$E$304,D7) -> 950 | H7: =IF(G7=0,"",_xlfn.MAXIFS(Payments!$A$5:$A$304,Payments!$B$5:$B$304,A7,Payments!$E$5:$E$304,D7)) -> 46266 | I7: =IF(E7>Settings!$B$4,0,IF(G7>=F7,MAX(0,H7-E7),Settings!$B$4-E7)) -> 0 | J7: =IF(I7>INDEX(Tenancies!$I$5:$I$50,MATCH(A7,Tenancies!$A$5:$A$50,0)),INDEX(Tenancies!$J$5:$J$50,MATCH(A7,Tenancies!$A$5:$A$50,0)),0) -> 0 | K7: =SUMIFS(Payments!$G$5:$G$304,Payments!$B$5:$B$304,A7,Payments!$E$5:$E$304,D7) -> 0 | L7: =IF(E7>Settings!$B$4,0,MAX(0,F7+J7-G7-K7)) -> 0 | M7: =IF(E7>Settings!$B$4,"Not due",IF(L7<=0,IF(I7>INDEX(Tenancies!$I$5:$I$50,MATCH(A7,Tenancies!$A$5:$A$50,0)),"Paid late","Paid"),IF(G7>=F7,"Fee due",IF(G7>0,"Partial","Overdue")))) -> Paid
A8: T01 | B8: =IFERROR(INDEX(Tenancies!$B$5:$B$50,MATCH(A8,Tenancies!$A$5:$A$50,0)),"") -> P01 | C8: =IFERROR(INDEX(Tenancies!$D$5:$D$50,MATCH(A8,Tenancies!$A$5:$A$50,0)),"") -> J. Carter | D8: 46296 | E8: =DATE(YEAR(D8),MONTH(D8),INDEX(Tenancies!$H$5:$H$50,MATCH(A8,Tenancies!$A$5:$A$50,0))) -> 46296 | F8: =INDEX(Tenancies!$G$5:$G$50,MATCH(A8,Tenancies!$A$5:$A$50,0)) -> 950 | G8: =SUMIFS(Payments!$F$5:$F$304,Payments!$B$5:$B$304,A8,Payments!$E$5:$E$304,D8) -> 950 | H8: =IF(G8=0,"",_xlfn.MAXIFS(Payments!$A$5:$A$304,Payments!$B$5:$B$304,A8,Payments!$E$5:$E$304,D8)) -> 46296 | I8: =IF(E8>Settings!$B$4,0,IF(G8>=F8,MAX(0,H8-E8),Settings!$B$4-E8)) -> 0 | J8: =IF(I8>INDEX(Tenancies!$I$5:$I$50,MATCH(A8,Tenancies!$A$5:$A$50,0)),INDEX(Tenancies!$J$5:$J$50,MATCH(A8,Tenancies!$A$5:$A$50,0)),0) -> 0 | K8: =SUMIFS(Payments!$G$5:$G$304,Payments!$B$5:$B$304,A8,Payments!$E$5:$E$304,D8) -> 0 | L8: =IF(E8>Settings!$B$4,0,MAX(0,F8+J8-G8-K8)) -> 0 | M8: =IF(E8>Settings!$B$4,"Not due",IF(L8<=0,IF(I8>INDEX(Tenancies!$I$5:$I$50,MATCH(A8,Tenancies!$A$5:$A$50,0)),"Paid late","Paid"),IF(G8>=F8,"Fee due",IF(G8>0,"Partial","Overdue")))) -> Paid
A9: T01 | B9: =IFERROR(INDEX(Tenancies!$B$5:$B$50,MATCH(A9,Tenancies!$A$5:$A$50,0)),"") -> P01 | C9: =IFERROR(INDEX(Tenancies!$D$5:$D$50,MATCH(A9,Tenancies!$A$5:$A$50,0)),"") -> J. Carter | D9: 46327 | E9: =DATE(YEAR(D9),MONTH(D9),INDEX(Tenancies!$H$5:$H$50,MATCH(A9,Tenancies!$A$5:$A$50,0))) -> 46327 | F9: =INDEX(Tenancies!$G$5:$G$50,MATCH(A9,Tenancies!$A$5:$A$50,0)) -> 950 | G9: =SUMIFS(Payments!$F$5:$F$304,Payments!$B$5:$B$304,A9,Payments!$E$5:$E$304,D9) -> 0 | H9: =IF(G9=0,"",_xlfn.MAXIFS(Payments!$A$5:$A$304,Payments!$B$5:$B$304,A9,Payments!$E$5:$E$304,D9)) | I9: =IF(E9>Settings!$B$4,0,IF(G9>=F9,MAX(0,H9-E9),Settings!$B$4-E9)) -> 0 | J9: =IF(I9>INDEX(Tenancies!$I$5:$I$50,MATCH(A9,Tenancies!$A$5:$A$50,0)),INDEX(Tenancies!$J$5:$J$50,MATCH(A9,Tenancies!$A$5:$A$50,0)),0) -> 0 | K9: =SUMIFS(Payments!$G$5:$G$304,Payments!$B$5:$B$304,A9,Payments!$E$5:$E$304,D9) -> 0 | L9: =IF(E9>Settings!$B$4,0,MAX(0,F9+J9-G9-K9)) -> 0 | M9: =IF(E9>Settings!$B$4,"Not due",IF(L9<=0,IF(I9>INDEX(Tenancies!$I$5:$I$50,MATCH(A9,Tenancies!$A$5:$A$50,0)),"Paid late","Paid"),IF(G9>=F9,"Fee due",IF(G9>0,"Partial","Overdue")))) -> Not due
A10: T01 | B10: =IFERROR(INDEX(Tenancies!$B$5:$B$50,MATCH(A10,Tenancies!$A$5:$A$50,0)),"") -> P01 | C10: =IFERROR(INDEX(Tenancies!$D$5:$D$50,MATCH(A10,Tenancies!$A$5:$A$50,0)),"") -> J. Carter | D10: 46357 | E10: =DATE(YEAR(D10),MONTH(D10),INDEX(Tenancies!$H$5:$H$50,MATCH(A10,Tenancies!$A$5:$A$50,0))) -> 46357 | F10: =INDEX(Tenancies!$G$5:$G$50,MATCH(A10,Tenancies!$A$5:$A$50,0)) -> 950 | G10: =SUMIFS(Payments!$F$5:$F$304,Payments!$B$5:$B$304,A10,Payments!$E$5:$E$304,D10) -> 0 | H10: =IF(G10=0,"",_xlfn.MAXIFS(Payments!$A$5:$A$304,Payments!$B$5:$B$304,A10,Payments!$E$5:$E$304,D10)) | I10: =IF(E10>Settings!$B$4,0,IF(G10>=F10,MAX(0,H10-E10),Settings!$B$4-E10)) -> 0 | J10: =IF(I10>INDEX(Tenancies!$I$5:$I$50,MATCH(A10,Tenancies!$A$5:$A$50,0)),INDEX(Tenancies!$J$5:$J$50,MATCH(A10,Tenancies!$A$5:$A$50,0)),0) -> 0 | K10: =SUMIFS(Payments!$G$5:$G$304,Payments!$B$5:$B$304,A10,Payments!$E$5:$E$304,D10) -> 0 | L10: =IF(E10>Settings!$B$4,0,MAX(0,F10+J10-G10-K10)) -> 0 | M10: =IF(E10>Settings!$B$4,"Not due",IF(L10<=0,IF(I10>INDEX(Tenancies!$I$5:$I$50,MATCH(A10,Tenancies!$A$5:$A$50,0)),"Paid late","Paid"),IF(G10>=F10,"Fee due",IF(G10>0,"Partial","Overdue")))) -> Not due
A11: T02 | B11: =IFERROR(INDEX(Tenancies!$B$5:$B$50,MATCH(A11,Tenancies!$A$5:$A$50,0)),"") -> P02 | C11: =IFERROR(INDEX(Tenancies!$D$5:$D$50,MATCH(A11,Tenancies!$A$5:$A$50,0)),"") -> M. Patel | D11: 46204 | E11: =DATE(YEAR(D11),MONTH(D11),INDEX(Tenancies!$H$5:$H$50,MATCH(A11,Tenancies!$A$5:$A$50,0))) -> 46208 | F11: =INDEX(Tenancies!$G$5:$G$50,MATCH(A11,Tenancies!$A$5:$A$50,0)) -> 1350 | G11: =SUMIFS(Payments!$F$5:$F$304,Payments!$B$5:$B$304,A11,Payments!$E$5:$E$304,D11) -> 1350 | H11: =IF(G11=0,"",_xlfn.MAXIFS(Payments!$A$5:$A$304,Payments!$B$5:$B$304,A11,Payments!$E$5:$E$304,D11)) -> 46207 | I11: =IF(E11>Settings!$B$4,0,IF(G11>=F11,MAX(0,H11-E11),Settings!$B$4-E11)) -> 0 | J11: =IF(I11>INDEX(Tenancies!$I$5:$I$50,MATCH(A11,Tenancies!$A$5:$A$50,0)),INDEX(Tenancies!$J$5:$J$50,MATCH(A11,Tenancies!$A$5:$A$50,0)),0) -> 0 | K11: =SUMIFS(Payments!$G$5:$G$304,Payments!$B$5:$B$304,A11,Payments!$E$5:$E$304,D11) -> 0 | L11: =IF(E11>Settings!$B$4,0,MAX(0,F11+J11-G11-K11)) -> 0 | M11: =IF(E11>Settings!$B$4,"Not due",IF(L11<=0,IF(I11>INDEX(Tenancies!$I$5:$I$50,MATCH(A11,Tenancies!$A$5:$A$50,0)),"Paid late","Paid"),IF(G11>=F11,"Fee due",IF(G11>0,"Partial","Overdue")))) -> Paid
A12: T02 | B12: =IFERROR(INDEX(Tenancies!$B$5:$B$50,MATCH(A12,Tenancies!$A$5:$A$50,0)),"") -> P02 | C12: =IFERROR(INDEX(Tenancies!$D$5:$D$50,MATCH(A12,Tenancies!$A$5:$A$50,0)),"") -> M. Patel | D12: 46235 | E12: =DATE(YEAR(D12),MONTH(D12),INDEX(Tenancies!$H$5:$H$50,MATCH(A12,Tenancies!$A$5:$A$50,0))) -> 46239 | F12: =INDEX(Tenancies!$G$5:$G$50,MATCH(A12,Tenancies!$A$5:$A$50,0)) -> 1350 | G12: =SUMIFS(Payments!$F$5:$F$304,Payments!$B$5:$B$304,A12,Payments!$E$5:$E$304,D12) -> 1350 | H12: =IF(G12=0,"",_xlfn.MAXIFS(Payments!$A$5:$A$304,Payments!$B$5:$B$304,A12,Payments!$E$5:$E$304,D12)) -> 46238 | I12: =IF(E12>Settings!$B$4,0,IF(G12>=F12,MAX(0,H12-E12),Settings!$B$4-E12)) -> 0 | J12: =IF(I12>INDEX(Tenancies!$I$5:$I$50,MATCH(A12,Tenancies!$A$5:$A$50,0)),INDEX(Tenancies!$J$5:$J$50,MATCH(A12,Tenancies!$A$5:$A$50,0)),0) -> 0 | K12: =SUMIFS(Payments!$G$5:$G$304,Payments!$B$5:$B$304,A12,Payments!$E$5:$E$304,D12) -> 0 | L12: =IF(E12>Settings!$B$4,0,MAX(0,F12+J12-G12-K12)) -> 0 | M12: =IF(E12>Settings!$B$4,"Not due",IF(L12<=0,IF(I12>INDEX(Tenancies!$I$5:$I$50,MATCH(A12,Tenancies!$A$5:$A$50,0)),"Paid late","Paid"),IF(G12>=F12,"Fee due",IF(G12>0,"Partial","Overdue")))) -> Paid
A13: T02 | B13: =IFERROR(INDEX(Tenancies!$B$5:$B$50,MATCH(A13,Tenancies!$A$5:$A$50,0)),"") -> P02 | C13: =IFERROR(INDEX(Tenancies!$D$5:$D$50,MATCH(A13,Tenancies!$A$5:$A$50,0)),"") -> M. Patel | D13: 46266 | E13: =DATE(YEAR(D13),MONTH(D13),INDEX(Tenancies!$H$5:$H$50,MATCH(A13,Tenancies!$A$5:$A$50,0))) -> 46270 | F13: =INDEX(Tenancies!$G$5:$G$50,MATCH(A13,Tenancies!$A$5:$A$50,0)) -> 1350 | G13: =SUMIFS(Payments!$F$5:$F$304,Payments!$B$5:$B$304,A13,Payments!$E$5:$E$304,D13) -> 1350 | H13: =IF(G13=0,"",_xlfn.MAXIFS(Payments!$A$5:$A$304,Payments!$B$5:$B$304,A13,Payments!$E$5:$E$304,D13)) -> 46280 | I13: =IF(E13>Settings!$B$4,0,IF(G13>=F13,MAX(0,H13-E13),Settings!$B$4-E13)) -> 10 | J13: =IF(I13>INDEX(Tenancies!$I$5:$I$50,MATCH(A13,Tenancies!$A$5:$A$50,0)),INDEX(Tenancies!$J$5:$J$50,MATCH(A13,Tenancies!$A$5:$A$50,0)),0) -> 40 | K13: =SUMIFS(Payments!$G$5:$G$304,Payments!$B$5:$B$304,A13,Payments!$E$5:$E$304,D13) -> 40 | L13: =IF(E13>Settings!$B$4,0,MAX(0,F13+J13-G13-K13)) -> 0 | M13: =IF(E13>Settings!$B$4,"Not due",IF(L13<=0,IF(I13>INDEX(Tenancies!$I$5:$I$50,MATCH(A13,Tenancies!$A$5:$A$50,0)),"Paid late","Paid"),IF(G13>=F13,"Fee due",IF(G13>0,"Partial","Overdue")))) -> Paid late
A14: T02 | B14: =IFERROR(INDEX(Tenancies!$B$5:$B$50,MATCH(A14,Tenancies!$A$5:$A$50,0)),"") -> P02 | C14: =IFERROR(INDEX(Tenancies!$D$5:$D$50,MATCH(A14,Tenancies!$A$5:$A$50,0)),"") -> M. Patel | D14: 46296 | E14: =DATE(YEAR(D14),MONTH(D14),INDEX(Tenancies!$H$5:$H$50,MATCH(A14,Tenancies!$A$5:$A$50,0))) -> 46300 | F14: =INDEX(Tenancies!$G$5:$G$50,MATCH(A14,Tenancies!$A$5:$A$50,0)) -> 1350 | G14: =SUMIFS(Payments!$F$5:$F$304,Payments!$B$5:$B$304,A14,Payments!$E$5:$E$304,D14) -> 1350 | H14: =IF(G14=0,"",_xlfn.MAXIFS(Payments!$A$5:$A$304,Payments!$B$5:$B$304,A14,Payments!$E$5:$E$304,D14)) -> 46299 | I14: =IF(E14>Settings!$B$4,0,IF(G14>=F14,MAX(0,H14-E14),Settings!$B$4-E14)) -> 0 | J14: =IF(I14>INDEX(Tenancies!$I$5:$I$50,MATCH(A14,Tenancies!$A$5:$A$50,0)),INDEX(Tenancies!$J$5:$J$50,MATCH(A14,Tenancies!$A$5:$A$50,0)),0) -> 0 | K14: =SUMIFS(Payments!$G$5:$G$304,Payments!$B$5:$B$304,A14,Payments!$E$5:$E$304,D14) -> 0 | L14: =IF(E14>Settings!$B$4,0,MAX(0,F14+J14-G14-K14)) -> 0 | M14: =IF(E14>Settings!$B$4,"Not due",IF(L14<=0,IF(I14>INDEX(Tenancies!$I$5:$I$50,MATCH(A14,Tenancies!$A$5:$A$50,0)),"Paid late","Paid"),IF(G14>=F14,"Fee due",IF(G14>0,"Partial","Overdue")))) -> Paid
A15: T02 | B15: =IFERROR(INDEX(Tenancies!$B$5:$B$50,MATCH(A15,Tenancies!$A$5:$A$50,0)),"") -> P02 | C15: =IFERROR(INDEX(Tenancies!$D$5:$D$50,MATCH(A15,Tenancies!$A$5:$A$50,0)),"") -> M. Patel | D15: 46327 | E15: =DATE(YEAR(D15),MONTH(D15),INDEX(Tenancies!$H$5:$H$50,MATCH(A15,Tenancies!$A$5:$A$50,0))) -> 46331 | F15: =INDEX(Tenancies!$G$5:$G$50,MATCH(A15,Tenancies!$A$5:$A$50,0)) -> 1350 | G15: =SUMIFS(Payments!$F$5:$F$304,Payments!$B$5:$B$304,A15,Payments!$E$5:$E$304,D15) -> 0 | H15: =IF(G15=0,"",_xlfn.MAXIFS(Payments!$A$5:$A$304,Payments!$B$5:$B$304,A15,Payments!$E$5:$E$304,D15)) | I15: =IF(E15>Settings!$B$4,0,IF(G15>=F15,MAX(0,H15-E15),Settings!$B$4-E15)) -> 0 | J15: =IF(I15>INDEX(Tenancies!$I$5:$I$50,MATCH(A15,Tenancies!$A$5:$A$50,0)),INDEX(Tenancies!$J$5:$J$50,MATCH(A15,Tenancies!$A$5:$A$50,0)),0) -> 0 | K15: =SUMIFS(Payments!$G$5:$G$304,Payments!$B$5:$B$304,A15,Payments!$E$5:$E$304,D15) -> 0 | L15: =IF(E15>Settings!$B$4,0,MAX(0,F15+J15-G15-K15)) -> 0 | M15: =IF(E15>Settings!$B$4,"Not due",IF(L15<=0,IF(I15>INDEX(Tenancies!$I$5:$I$50,MATCH(A15,Tenancies!$A$5:$A$50,0)),"Paid late","Paid"),IF(G15>=F15,"Fee due",IF(G15>0,"Partial","Overdue")))) -> Not due
A16: T02 | B16: =IFERROR(INDEX(Tenancies!$B$5:$B$50,MATCH(A16,Tenancies!$A$5:$A$50,0)),"") -> P02 | C16: =IFERROR(INDEX(Tenancies!$D$5:$D$50,MATCH(A16,Tenancies!$A$5:$A$50,0)),"") -> M. Patel | D16: 46357 | E16: =DATE(YEAR(D16),MONTH(D16),INDEX(Tenancies!$H$5:$H$50,MATCH(A16,Tenancies!$A$5:$A$50,0))) -> 46361 | F16: =INDEX(Tenancies!$G$5:$G$50,MATCH(A16,Tenancies!$A$5:$A$50,0)) -> 1350 | G16: =SUMIFS(Payments!$F$5:$F$304,Payments!$B$5:$B$304,A16,Payments!$E$5:$E$304,D16) -> 0 | H16: =IF(G16=0,"",_xlfn.MAXIFS(Payments!$A$5:$A$304,Payments!$B$5:$B$304,A16,Payments!$E$5:$E$304,D16)) | I16: =IF(E16>Settings!$B$4,0,IF(G16>=F16,MAX(0,H16-E16),Settings!$B$4-E16)) -> 0 | J16: =IF(I16>INDEX(Tenancies!$I$5:$I$50,MATCH(A16,Tenancies!$A$5:$A$50,0)),INDEX(Tenancies!$J$5:$J$50,MATCH(A16,Tenancies!$A$5:$A$50,0)),0) -> 0 | K16: =SUMIFS(Payments!$G$5:$G$304,Payments!$B$5:$B$304,A16,Payments!$E$5:$E$304,D16) -> 0 | L16: =IF(E16>Settings!$B$4,0,MAX(0,F16+J16-G16-K16)) -> 0 | M16: =IF(E16>Settings!$B$4,"Not due",IF(L16<=0,IF(I16>INDEX(Tenancies!$I$5:$I$50,MATCH(A16,Tenancies!$A$5:$A$50,0)),"Paid late","Paid"),IF(G16>=F16,"Fee due",IF(G16>0,"Partial","Overdue")))) -> Not due
... A28: T04 | B28: =IFERROR(INDEX(Tenancies!$B$5:$B$50,MATCH(A28,Tenancies!$A$5:$A$50,0)),"") -> P04 | C28: =IFERROR(INDEX(Tenancies!$D$5:$D$50,MATCH(A28,Tenancies!$A$5:$A$50,0)),"") -> A. Okafor | D28: 46357 | E28: =DATE(YEAR(D28),MONTH(D28),INDEX(Tenancies!$H$5:$H$50,MATCH(A28,Tenancies!$A$5:$A$50,0))) -> 46366 | F28: =INDEX(Tenancies!$G$5:$G$50,MATCH(A28,Tenancies!$A$5:$A$50,0)) -> 1600 | G28: =SUMIFS(Payments!$F$5:$F$304,Payments!$B$5:$B$304,A28,Payments!$E$5:$E$304,D28) -> 0 | H28: =IF(G28=0,"",_xlfn.MAXIFS(Payments!$A$5:$A$304,Payments!$B$5:$B$304,A28,Payments!$E$5:$E$304,D28)) | I28: =IF(E28>Settings!$B$4,0,IF(G28>=F28,MAX(0,H28-E28),Settings!$B$4-E28)) -> 0 | J28: =IF(I28>INDEX(Tenancies!$I$5:$I$50,MATCH(A28,Tenancies!$A$5:$A$50,0)),INDEX(Tenancies!$J$5:$J$50,MATCH(A28,Tenancies!$A$5:$A$50,0)),0) -> 0 | K28: =SUMIFS(Payments!$G$5:$G$304,Payments!$B$5:$B$304,A28,Payments!$E$5:$E$304,D28) -> 0 | L28: =IF(E28>Settings!$B$4,0,MAX(0,F28+J28-G28-K28)) -> 0 | M28: =IF(E28>Settings!$B$4,"Not due",IF(L28<=0,IF(I28>INDEX(Tenancies!$I$5:$I$50,MATCH(A28,Tenancies!$A$5:$A$50,0)),"Paid late","Paid"),IF(G28>=F28,"Fee due",IF(G28>0,"Partial","Overdue")))) -> Not due

Sheet Tenancies
A1: Tenancies
A2: Rent, due day, grace period and late fee per tenancy (fictitious tenants).
A4: Tenancy ID | B4: Property ID | C4: Address | D4: Tenant | E4: Start date | F4: End date | G4: Monthly rent (£) | H4: Due day of month | I4: Grace days | J4: Late fee (£) | K4: Status
A5: T01 | B5: P01 | C5: =IFERROR(INDEX(Properties!$B$5:$B$50,MATCH(B5,Properties!$A$5:$A$50,0)),"") -> 12 Elm Road, Birmingham B15 | D5: J. Carter | E5: 46023 | F5: 46568 | G5: 950 | H5: 1 | I5: 5 | J5: 50 | K5: =IF(Settings!$B$4>F5,"Ended",IF(Settings!$B$4<E5,"Future",IF(F5-Settings!$B$4<=60,"Ending soon","Active"))) -> Active
A6: T02 | B6: P02 | C6: =IFERROR(INDEX(Properties!$B$5:$B$50,MATCH(B6,Properties!$A$5:$A$50,0)),"") -> 48 Oak Street, Birmingham B29 | D6: M. Patel | E6: 45905 | F6: 46387 | G6: 1350 | H6: 5 | I6: 5 | J6: 40 | K6: =IF(Settings!$B$4>F6,"Ended",IF(Settings!$B$4<E6,"Future",IF(F6-Settings!$B$4<=60,"Ending soon","Active"))) -> Active
A7: T03 | B7: P03 | C7: =IFERROR(INDEX(Properties!$B$5:$B$50,MATCH(B7,Properties!$A$5:$A$50,0)),"") -> 7 Canal View, Birmingham B1 | D7: S. Nowak | E7: 46082 | F7: 46446 | G7: 875 | H7: 1 | I7: 5 | J7: 35 | K7: =IF(Settings!$B$4>F7,"Ended",IF(Settings!$B$4<E7,"Future",IF(F7-Settings!$B$4<=60,"Ending soon","Active"))) -> Active
A8: T04 | B8: P04 | C8: =IFERROR(INDEX(Properties!$B$5:$B$50,MATCH(B8,Properties!$A$5:$A$50,0)),"") -> 221 Bristol Road, Birmingham B5 | D8: A. Okafor | E8: 45971 | F8: 46335 | G8: 1600 | H8: 10 | I8: 5 | J8: 75 | K8: =IF(Settings!$B$4>F8,"Ended",IF(Settings!$B$4<E8,"Future",IF(F8-Settings!$B$4<=60,"Ending soon","Active"))) -> Ending soon

Sheet Properties
A1: Properties
A2: One row per property. The Property ID drives every lookup.
A4: Property ID | B4: Address | C4: Type | D4: Bedrooms | E4: Notes
A5: P01 | B5: 12 Elm Road, Birmingham B15 | C5: Flat | D5: 2 | E5: Demo data
A6: P02 | B6: 48 Oak Street, Birmingham B29 | C6: Terraced house | D6: 3 | E6: Demo data
A7: P03 | B7: 7 Canal View, Birmingham B1 | C7: Flat | D7: 1 | E7: Demo data
A8: P04 | B8: 221 Bristol Road, Birmingham B5 | C8: Semi-detached house | D8: 4 | E8: Demo data

Sheet Expenses
A1: Property expenses
A2: Costs paid per property (deducted before shareholder returns).
A4: Date | B4: Property ID | C4: Category | D4: Amount (£) | E4: Notes
A5: 46206 | B5: P01 | C5: Insurance | D5: 180 | E5: Annual landlord policy
A6: 46218 | B6: P03 | C6: Service charge | D6: 600 | E6: Half-year service charge
A7: 46246 | B7: P02 | C7: Repairs & maintenance | D7: 420 | E7: Boiler repair
A8: 46267 | B8: P04 | C8: Compliance & safety | D8: 90 | E8: Gas safety certificate
A9: 46285 | B9: P02 | C9: Compliance & safety | D9: 75 | E9: EICR follow-up
A10: 46301 | B10: P04 | C10: Repairs & maintenance | D10: 850 | E10: Roof tiles after storm
A11: 46309 | B11: P01 | C11: Letting fees | D11: 120 | E11: Tenancy renewal admin

Sheet Ownership
A1: Ownership & shareholder returns
A2: Each shareholder's return varies by the properties they own and how each property performs.
A4: Property ID | B4: Net income (£) | C4: R. Hughes % | D4: L. Bennett % | E4: K. Shah % | F4: Check (must be 100%)
A5: =Properties!A5 -> P01 | B5: =INDEX(Dashboard!$H$16:$H$19,MATCH(A5,Dashboard!$A$16:$A$19,0)) -> 3196 | C5: 0.5 | D5: 0.5 | E5: 0 | F5: =SUM(C5:E5) -> 1
A6: =Properties!A6 -> P02 | B6: =INDEX(Dashboard!$H$16:$H$19,MATCH(A6,Dashboard!$A$16:$A$19,0)) -> 4509.8 | C6: 0.4 | D6: 0.3 | E6: 0.3 | F6: =SUM(C6:E6) -> 1
A7: =Properties!A7 -> P03 | B7: =INDEX(Dashboard!$H$16:$H$19,MATCH(A7,Dashboard!$A$16:$A$19,0)) -> 2275 | C7: 0 | D7: 0.5 | E7: 0.5 | F7: =SUM(C7:E7) -> 1
A8: =Properties!A8 -> P04 | B8: =INDEX(Dashboard!$H$16:$H$19,MATCH(A8,Dashboard!$A$16:$A$19,0)) -> 3476 | C8: 0.34 | D8: 0.33 | E8: 0.33 | F8: =SUM(C8:E8) -> 1
A11: Shareholder statement
A12: Earned = sum over properties of (net income x ownership %). Next distribution = earned - already distributed.
A14: Shareholder | B14: P01 share (£) | C14: P02 share (£) | D14: P03 share (£) | E14: P04 share (£) | F14: Earned to date (£) | G14: Distributed (£) | H14: Next distribution (£)
A15: R. Hughes | B15: =$B$5*$C$5 -> 1598 | C15: =$B$6*$C$6 -> 1803.92 | D15: =$B$7*$C$7 -> 0 | E15: =$B$8*$C$8 -> 1181.84 | F15: =SUM(B15:E15) -> 4583.76 | G15: =SUMIFS(Distributions!$C$5:$C$104,Distributions!$B$5:$B$104,A15) -> 1800 | H15: =MAX(0,F15-G15) -> 2783.76
A16: L. Bennett | B16: =$B$5*$D$5 -> 1598 | C16: =$B$6*$D$6 -> 1352.94 | D16: =$B$7*$D$7 -> 1137.5 | E16: =$B$8*$D$8 -> 1147.08 | F16: =SUM(B16:E16) -> 5235.52 | G16: =SUMIFS(Distributions!$C$5:$C$104,Distributions!$B$5:$B$104,A16) -> 1600 | H16: =MAX(0,F16-G16) -> 3635.52
A17: K. Shah | B17: =$B$5*$E$5 -> 0 | C17: =$B$6*$E$6 -> 1352.94 | D17: =$B$7*$E$7 -> 1137.5 | E17: =$B$8*$E$8 -> 1147.08 | F17: =SUM(B17:E17) -> 3637.52 | G17: =SUMIFS(Distributions!$C$5:$C$104,Distributions!$B$5:$B$104,A17) -> 1500 | H17: =MAX(0,F17-G17) -> 2137.52
A18: Total | B18: =SUM(B15:B17) -> 3196 | C18: =SUM(C15:C17) -> 4509.8 | D18: =SUM(D15:D17) -> 2275 | E18: =SUM(E15:E17) -> 3476 | F18: =SUM(F15:F17) -> 13456.8 | G18: =SUM(G15:G17) -> 4900 | H18: =SUM(H15:H17) -> 8556.8

Sheet Distributions
A1: Distributions paid
A2: Record every payout to a shareholder.
A4: Date | B4: Shareholder | C4: Amount (£) | D4: Notes
A5: 46295 | B5: R. Hughes | C5: 1800 | D5: Q3 payout
A6: 46295 | B6: L. Bennett | C6: 1600 | D6: Q3 payout
A7: 46295 | B7: K. Shah | C7: 1500 | D7: Q3 payout

Sheet Settings
A1: Settings
A2: Blue text on yellow = inputs you can change
A4: As-of date | B4: 46318 | C4: Demo uses a fixed date so the numbers stay stable. In live use replace with =TODAY().
A5: Management fee (% of rent collected) | B5: 0.08 | C5: Assumption for the demo: fee kept by the managing agent before shareholder distributions.
A6: Currency | B6: GBP (£) | C6: Display only.
A8: Lists used in drop-downs
A9: Payment method | B9: Expense category
A10: Standing order | B10: Repairs & maintenance
A11: Bank transfer | B11: Insurance
A12: Card | B12: Service charge
A13: Cash | B13: Compliance & safety
B14: Letting fees
B15: Other
